mock_file_tree/__init__.py
mock_file_tree/models/__init__.py
mock_file_tree/models/exceptions.py
mock_file_tree/models/file_tree.py
mock_file_tree/models/mock_file_tree.py
mock_file_tree/models/unsupported.py
mock_file_tree/utils/__init__.py
mock_file_tree/utils/paths.py
mock_file_tree-1.1.3.dist-info/LICENSE.md
mock_file_tree-1.1.3.dist-info/METADATA
mock_file_tree-1.1.3.dist-info/WHEEL
mock_file_tree-1.1.3.dist-info/top_level.txt
mock_file_tree-1.1.3.dist-info/RECORD
