Metadata-Version: 2.1
Name: mock-file-tree
Version: 1.1.3
Summary: A simple interface to mock the os module with a virtual file tree.
Home-page: https://github.com/joellefkowitz/mock-file-tree
Author: Joel Lefkowitz
Author-email: joellefkowitz@hotmail.com
License: UNKNOWN
Project-URL: Bug Tracker, https://github.com/joellefkowitz/mock-file-tree/issues
Project-URL: CI, https://github.com/joellefkowitz/mock-file-tree/actions
Project-URL: Documentation, https://mock-file-tree.readthedocs.io/en/latest/
Project-URL: Source Code, https://github.com/joellefkowitz/mock-file-tree
Keywords: files,mock,testing
Platform: UNKNOWN
Classifier: Intended Audience :: Developers
Classifier: License :: OSI Approved :: MIT License
Classifier: Programming Language :: Python :: 3.6
Classifier: Programming Language :: Python :: 3.7
Classifier: Programming Language :: Python :: 3.8
Classifier: Programming Language :: Python :: 3.9
Classifier: Operating System :: OS Independent
Classifier: Topic :: Software Development :: Libraries :: Python Modules
Requires-Python: >= 3.6
Requires-Dist: dataclasses
Requires-Dist: types-dataclasses
Provides-Extra: all
Requires-Dist: mypy ; extra == 'all'
Requires-Dist: pylint ; extra == 'all'
Requires-Dist: bandit ; extra == 'all'
Requires-Dist: autoflake ; extra == 'all'
Requires-Dist: black ; extra == 'all'
Requires-Dist: isort ; extra == 'all'
Requires-Dist: coverage ; extra == 'all'
Requires-Dist: pytest-mocha ; extra == 'all'
Requires-Dist: pytest-sugar ; extra == 'all'
Requires-Dist: pytest ; extra == 'all'
Requires-Dist: tox ; extra == 'all'
Requires-Dist: bump2version ; extra == 'all'
Requires-Dist: quickdocs ; extra == 'all'
Requires-Dist: twine ; extra == 'all'
Requires-Dist: wheel ; extra == 'all'
Provides-Extra: formatters
Requires-Dist: autoflake ; extra == 'formatters'
Requires-Dist: black ; extra == 'formatters'
Requires-Dist: isort ; extra == 'formatters'
Provides-Extra: linters
Requires-Dist: mypy ; extra == 'linters'
Requires-Dist: pylint ; extra == 'linters'
Requires-Dist: bandit ; extra == 'linters'
Provides-Extra: release
Requires-Dist: bump2version ; extra == 'release'
Requires-Dist: quickdocs ; extra == 'release'
Requires-Dist: twine ; extra == 'release'
Requires-Dist: wheel ; extra == 'release'
Provides-Extra: tests
Requires-Dist: coverage ; extra == 'tests'
Requires-Dist: pytest-mocha ; extra == 'tests'
Requires-Dist: pytest-sugar ; extra == 'tests'
Requires-Dist: pytest ; extra == 'tests'
Requires-Dist: tox ; extra == 'tests'
